{
  "context": "generalLedger",
  "nameSpace": "XM",
  "type": "BankReconciliationUnreconciled",
  "table": "xt.unrec",
  "comment": "Bank Reconcilition Unreconciled Map",
  "privileges": {
    "all": {
      "create": false,
      "read": true,
      "update": false,
      "delete": false
    }
  },
  "properties": [
    {
      "name": "guid",
      "attr": {
        "type": "Number",
        "column": "jrnl_id",
        "isPrimaryKey": true
      }
    },
    {
      "name": "bankReconciliation",
      "toOne": {
        "type": "BankReconciliation",
        "column": "bankrec_id"
      }
    },
    {
      "name": "date",
      "attr": {
        "type": "String",
        "column": "jrnl_date"
      }
    },
    {
      "name": "documentType",
      "attr": {
        "type": "String",
        "column": "jrnl_doctype"
      }
    },
    {
      "name": "documentNumber",
      "attr": {
        "type": "Number",
        "column": "jrnl_docnumber"
      }
    },
    {
      "name": "amount",
      "attr": {
        "type": "Number",
        "column": "jrnl_amount"
      }
    },
    {
      "name": "notes",
      "attr": {
        "type": "String",
        "column": "jrnl_notes"
      }
    }
  ],
  "isNestedOnly": true,
  "isSystem": true
}
